Workbook

Sheet Instrucciones
A1: CÓMO SE USA
A3: PARA EL AGENTE
A4: 1. Ve a la hoja "Calculadora".
A5: 2. Rellena solo las cuatro celdas AMARILLAS de la sección 1. La columna "Ejemplo" te enseña el formato que espera cada una.
A6: 3. El resto se calcula solo. No hace falta que toques nada más.
A7: 4. Nada de lo que escribas sale de este archivo. No se envía a ningún sitio, no lleva macros y no necesitas compartir ninguna cifra con nadie.
A9: PARA LA TEAM LEADER — ANTES DE ENVIARLO
A10: 1. Abre la hoja "Parametros_MC" y rellena las cinco celdas amarillas con los datos REALES de tu Market Center.
A11: 2. Comprueba la fila "Honorarios anuales necesarios para alcanzar el tope": es el número sobre el que va a girar la conversación.
A12: 3. Guarda y envía. Si quieres, oculta la hoja "Parametros_MC" (clic derecho en la pestaña → Ocultar) para que el agente vea solo su calculadora.
A13: 4. No envíes el archivo con los parámetros vacíos: saldrían ceros y perderías la conversación.
A15: LEYENDA DE COLORES
... A19: Gris → columna de ejemplo y notas aclaratorias.

Sheet Calculadora
A1: ¿CUÁNTO TE QUEDARÍAS CON OTRO MODELO?
A2: Rellena solo las celdas AMARILLAS. Nada de lo que escribas sale de este archivo: no se envía a ningún sitio y no hace falta que compartas ni un número.
A3: =IF(OR(Parametros_MC!$B$6=0,Parametros_MC!$B$7=0),"⚠ FALTAN LOS PARÁMETROS DEL MARKET CENTER. Los resultados de abajo NO son válidos: ve a la hoja Parametros_MC y rellena las celdas amarillas.","") -> ⚠ FALTAN LOS PARÁMETROS DEL MARKET CENTER. Los resultados de abajo NO son válidos: ve a la hoja Parametros_MC y rellena las celdas amarillas.
A4: 1 · TUS NÚMEROS
A5: Concepto | B5: Tu dato | C5: Ejemplo | D5: Nota
A6: Operaciones cerradas en los últimos 12 meses | C6: 12 | D6: Compraventas y alquileres que hayas facturado.
A7: Honorarios medios por operación (€) | C7: 18000 | D7: Lo que factura la agencia por la operación, NO lo que cobras tú.
A8: % de los honorarios que te quedas hoy | C8: 0.4 | D8: Tu reparto actual. Si te quedas 4.000 € de unos honorarios de 10.000 €, es 40%.
A9: Costes fijos que pagas tú al año (€) | C9: 2400 | D9: Puesto, portales, fotografía, marketing, cuotas. Lo que sale de tu bolsillo.
A11: Honorarios totales que generas al año | B11: =B6*B7 -> 0 | C11: =C6*C7 -> 216000 | D11: Es la cifra que factura tu agencia gracias a tu trabajo.
A13: 2 · LO QUE TE QUEDA HOY
A14: Te quedas (antes de costes) | B14: =B11*B8 -> 0 | C14: =C11*C8 -> 86400
A15: Menos tus costes fijos | B15: =-B9 -> 0 | C15: =-C9 -> -2400
A16: NETO ACTUAL | B16: =SUM(B14:B15) -> 0 | C16: =SUM(C14:C15) -> 84000
A18: 3 · LO QUE TE QUEDARÍA CON ESTE MODELO
A19: Honorarios totales que generas | B19: =B11 -> 0 | C19: =C11 -> 216000 | D19: Los mismos honorarios: cambia el reparto, no tu trabajo.
A20: Menos tu aportación al MC (con tope aplicado) | B20: =-MIN(B19*(1-Parametros_MC!$B$6),Parametros_MC!$B$7) -> 0 | C20: =-MIN(C19*(1-Parametros_MC!$B$6),Parametros_MC!$B$7) -> -216000 | D20: ESTA ES LA LÍNEA CLAVE: la aportación tiene tope. Al alcanzarlo, deja de descontarse.
A21: Menos royalty (con tope aplicado) | B21: =-MIN(B19*Parametros_MC!$B$8,Parametros_MC!$B$9) -> 0 | C21: =-MIN(C19*Parametros_MC!$B$8,Parametros_MC!$B$9) -> 0
A22: Menos cuotas fijas del MC | B22: =-Parametros_MC!$B$10 -> 0 | C22: =-Parametros_MC!$B$10 -> 0 | D22: Ojo: aquí ya no pagas portales ni fotografía. Eso lo cubre el MC.
A23: NETO CON ESTE MODELO | B23: =B19+B20+B21+B22 -> 0 | C23: =C19+C20+C21+C22 -> 0
A25: 4 · LA DIFERENCIA
A26: Diferencia al año | B26: =B23-B16 -> 0 | C26: =C23-C16 -> -84000
A27: Diferencia en porcentaje | B27: =IFERROR(IF(B16<=0,"—",B26/B16),"—") -> —
A28: % efectivo que te quedas hoy | B28: =IFERROR(IF(B11<=0,"—",B16/B11),"—") -> —
A29: % efectivo que te quedarías | B29: =IFERROR(IF(B11<=0,"—",B23/B11),"—") -> —
A31: 5 · EL TOPE (lo que casi nadie mira)
A32: Honorarios necesarios para alcanzar el tope | B32: =IFERROR(IF((1-Parametros_MC!$B$6)<=0,"—",Parametros_MC!$B$7/(1-Parametros_MC!$B$6)),"—") -> 0
A33: Operaciones que te hacen falta para eso | B33: =IFERROR(IF(OR(B7<=0,NOT(ISNUMBER(B32))),"—",B32/B7),"—") -> — | D33: Con tus honorarios medios actuales.
A34: ¿Llegas al tope con tu producción de hoy? | B34: =IFERROR(IF(NOT(ISNUMBER(B32)),"—",IF(B11>=B32,"SÍ","Todavía no")),"—") -> SÍ
A35: Lo que te quedas de cada euro pasado el tope | B35: =IFERROR(1-Parametros_MC!$B$8,"—") -> 1 | D35: Pasado el tope dejas de aportar al MC y solo te descuentan el royalty. Cuando el royalty también agota su tope, te quedas el 100%.
A37: 6 · Y SI CRECES (o si tienes un año flojo)
A38: Escenario | B38: Honorarios generados | C38: Neto hoy | D38: Neto con este modelo | E38: Diferencia
A39: Año flojo (-40%) | B39: =$B$11*0.6 -> 0 | C39: =$B$11*0.6*$B$8-$B$9 -> 0 | D39: =$B$11*0.6-MIN($B$11*0.6*(1-Parametros_MC!$B$6),Parametros_MC!$B$7)-MIN($B$11*0.6*Parametros_MC!$B$8,Parametros_MC!$B$9)-Parametros_MC!$B$10 -> 0 | E39: =D39-C39 -> 0
A40: Algo peor (-20%) | B40: =$B$11*0.8 -> 0 | C40: =$B$11*0.8*$B$8-$B$9 -> 0 | D40: =$B$11*0.8-MIN($B$11*0.8*(1-Parametros_MC!$B$6),Parametros_MC!$B$7)-MIN($B$11*0.8*Parametros_MC!$B$8,Parametros_MC!$B$9)-Parametros_MC!$B$10 -> 0 | E40: =D40-C40 -> 0
A41: Como ahora | B41: =$B$11*1 -> 0 | C41: =$B$11*1*$B$8-$B$9 -> 0 | D41: =$B$11*1-MIN($B$11*1*(1-Parametros_MC!$B$6),Parametros_MC!$B$7)-MIN($B$11*1*Parametros_MC!$B$8,Parametros_MC!$B$9)-Parametros_MC!$B$10 -> 0 | E41: =D41-C41 -> 0
A42: Creciendo (+25%) | B42: =$B$11*1.25 -> 0 | C42: =$B$11*1.25*$B$8-$B$9 -> 0 | D42: =$B$11*1.25-MIN($B$11*1.25*(1-Parametros_MC!$B$6),Parametros_MC!$B$7)-MIN($B$11*1.25*Parametros_MC!$B$8,Parametros_MC!$B$9)-Parametros_MC!$B$10 -> 0 | E42: =D42-C42 -> 0
A43: Buen año (+50%) | B43: =$B$11*1.5 -> 0 | C43: =$B$11*1.5*$B$8-$B$9 -> 0 | D43: =$B$11*1.5-MIN($B$11*1.5*(1-Parametros_MC!$B$6),Parametros_MC!$B$7)-MIN($B$11*1.5*Parametros_MC!$B$8,Parametros_MC!$B$9)-Parametros_MC!$B$10 -> 0 | E43: =D43-C43 -> 0
A44: El doble | B44: =$B$11*2 -> 0 | C44: =$B$11*2*$B$8-$B$9 -> 0 | D44: =$B$11*2-MIN($B$11*2*(1-Parametros_MC!$B$6),Parametros_MC!$B$7)-MIN($B$11*2*Parametros_MC!$B$8,Parametros_MC!$B$9)-Parametros_MC!$B$10 -> 0 | E44: =D44-C44 -> 0
A46: Fíjate en cómo se abre la diferencia cuanto más produces: es el efecto del tope. En los años flojos los dos modelos se parecen; en los buenos, no.
A48: Supuestos: el cálculo asume que mantienes el mismo número de operaciones y los mismos honorarios medios en los dos modelos, y no incluye el reparto de beneficios ni los ingresos por referencias. Los parámetros del Market Center están en la hoja "Parametros_MC" y los ha introducido la Team Leader.

Sheet Parametros_MC
A1: PARÁMETROS DEL MARKET CENTER — rellena esto ANTES de enviar el archivo
A3: ⚠️ Las celdas amarillas vienen VACÍAS a propósito. No invento las cifras de tu Market Center: cada MC tiene las suyas. Pon las reales antes de mandar el archivo a un candidato — si envías un número que luego no puedes sostener, pierdes al agente y la credibilidad corre entre la competencia.
A5: Parámetro | B5: Valor | C5: Qué poner aquí
A6: % de los honorarios que se queda el agente (antes del tope) | C6: El reparto de salida. Si el agente se queda el 70%, escribe 70%.
A7: Tope anual de aportación del agente al MC (cap, €) | C7: Lo máximo que el agente aporta al MC en su año de aniversario. Al alcanzarlo, deja de aportar.
A8: % de royalty sobre honorarios | C8: El porcentaje que va a la franquicia. Si no aplica en tu modelo, pon 0%.
A9: Tope anual de royalty (€) | C9: Lo máximo de royalty al año. Si no tiene tope, pon un número muy alto (p. ej. 999999).
A10: Cuotas fijas anuales del agente en el MC (€) | C10: Suma de cuotas, tecnología o puesto que paga el agente al año. Si el MC lo cubre todo, pon 0.
A13: COMPROBACIÓN
A14: Honorarios anuales necesarios para alcanzar el tope | B14: =IFERROR(IF((1-B6)<=0,"—",B7/(1-B6)),"—") -> 0 | C14: A partir de esta cifra de honorarios generados, el agente deja de aportar al MC. Es el número que más mueve la conversación.
A16: Fuente de los parámetros: datos del Market Center, introducidos por la Team Leader.
